LICENSE
MANIFEST.in
README.md
pyproject.toml
setup.py
dvrctl/__init__.py
dvrctl/deliver.py
dvrctl/general.py
dvrctl/get_resolve.py
dvrctl/media_pool.py
dvrctl/media_storage.py
dvrctl/project.py
dvrctl/project_manager.py
dvrctl/timeline.py
dvrctl.egg-info/PKG-INFO
dvrctl.egg-info/SOURCES.txt
dvrctl.egg-info/dependency_links.txt
dvrctl.egg-info/requires.txt
dvrctl.egg-info/top_level.txt